logfire_api/__init__.py
logfire_api/__init__.pyi
logfire_api/cli.pyi
logfire_api/exceptions.pyi
logfire_api/propagate.pyi
logfire_api/py.typed
logfire_api/query_client.pyi
logfire_api/types.pyi
logfire_api/version.pyi
logfire_api/_internal/__init__.pyi
logfire_api/_internal/ast_utils.pyi
logfire_api/_internal/async_.pyi
logfire_api/_internal/auth.pyi
logfire_api/_internal/baggage.pyi
logfire_api/_internal/cli.pyi
logfire_api/_internal/client.pyi
logfire_api/_internal/collect_system_info.pyi
logfire_api/_internal/config.pyi
logfire_api/_internal/config_params.pyi
logfire_api/_internal/constants.pyi
logfire_api/_internal/db_statement_summary.pyi
logfire_api/_internal/formatter.pyi
logfire_api/_internal/instrument.pyi
logfire_api/_internal/json_encoder.pyi
logfire_api/_internal/json_formatter.pyi
logfire_api/_internal/json_schema.pyi
logfire_api/_internal/json_types.pyi
logfire_api/_internal/logs.pyi
logfire_api/_internal/main.pyi
logfire_api/_internal/metrics.pyi
logfire_api/_internal/scrubbing.pyi
logfire_api/_internal/stack_info.pyi
logfire_api/_internal/tracer.pyi
logfire_api/_internal/ulid.pyi
logfire_api/_internal/utils.pyi
logfire_api/_internal/auto_trace/__init__.pyi
logfire_api/_internal/auto_trace/import_hook.pyi
logfire_api/_internal/auto_trace/rewrite_ast.pyi
logfire_api/_internal/auto_trace/types.pyi
logfire_api/_internal/cli/__init__.pyi
logfire_api/_internal/cli/auth.pyi
logfire_api/_internal/cli/prompt.pyi
logfire_api/_internal/cli/run.pyi
logfire_api/_internal/exporters/__init__.pyi
logfire_api/_internal/exporters/console.pyi
logfire_api/_internal/exporters/dynamic_batch.pyi
logfire_api/_internal/exporters/logs.pyi
logfire_api/_internal/exporters/otlp.pyi
logfire_api/_internal/exporters/processor_wrapper.pyi
logfire_api/_internal/exporters/quiet_metrics.pyi
logfire_api/_internal/exporters/remove_pending.pyi
logfire_api/_internal/exporters/tail_sampling.pyi
logfire_api/_internal/exporters/wrapper.pyi
logfire_api/_internal/integrations/__init__.pyi
logfire_api-4.14.0.dist-info/METADATA
logfire_api-4.14.0.dist-info/WHEEL
logfire_api-4.14.0.dist-info/RECORD
